simplesocialauthlib-0.3.1.dist-info/METADATA
simplesocialauthlib-0.3.1.dist-info/WHEEL
simplesocialauthlib-0.3.1.dist-info/entry_points.txt
simplesocialauthlib-0.3.1.dist-info/licenses/LICENSE
simplesocialauthlib/__init__.py
simplesocialauthlib/abstract.py
simplesocialauthlib/exceptions.py
simplesocialauthlib/providers/__init__.py
simplesocialauthlib/providers/github.py
simplesocialauthlib/providers/google.py
simplesocialauthlib/types.py
simplesocialauthlib/utils.py
simplesocialauthlib-0.3.1.dist-info/RECORD
