Metadata-Version: 2.1
Name: SimpleSocialAuthLib
Version: 0.3.1
Summary: SimpleSocialAuthLib is a Python library designed to simplify social authentication for various providers. It offers a straightforward interface for handling OAuth2 flows and retrieving user data from popular social platforms.
Author-Email: Macktireh <abdimack97@gmail.com>
License: MIT
Classifier: Programming Language :: Python
Classifier: Programming Language :: Python :: 3
Classifier: Programming Language :: Python :: 3.12
Classifier: Programming Language :: Python :: 3.13
Classifier: License :: OSI Approved :: MIT License
Classifier: Operating System :: OS Independent
Classifier: Intended Audience :: Developers
Classifier: Typing :: Typed
Classifier: Topic :: Software Development :: Libraries
Project-URL: Homepage, https://github.com/Macktireh/SimpleSocialAuthLib
Project-URL: Documentation, https://github.com/Macktireh/SimpleSocialAuthLib#readme
Project-URL: Repository, https://github.com/Macktireh/SimpleSocialAuthLib
Project-URL: Issues, https://github.com/Macktireh/SimpleSocialAuthLib/issues
Requires-Python: >=3.12
Provides-Extra: google
Requires-Dist: google-api-python-client>=2.177.0; extra == "google"
Requires-Dist: requests-oauthlib>=2.0.0; extra == "google"
Provides-Extra: github
Requires-Dist: requests>=2.32.4; extra == "github"
Provides-Extra: all
Requires-Dist: google-api-python-client>=2.177.0; extra == "all"
Requires-Dist: requests-oauthlib>=2.0.0; extra == "all"
Requires-Dist: requests>=2.32.4; extra == "all"
